sphinxcontrib/bibtex/__init__.py
sphinxcontrib/bibtex/bibfile.py
sphinxcontrib/bibtex/citation_target.py
sphinxcontrib/bibtex/directives.py
sphinxcontrib/bibtex/domain.py
sphinxcontrib/bibtex/foot_directives.py
sphinxcontrib/bibtex/foot_domain.py
sphinxcontrib/bibtex/foot_roles.py
sphinxcontrib/bibtex/nodes.py
sphinxcontrib/bibtex/plugin.py
sphinxcontrib/bibtex/py.typed
sphinxcontrib/bibtex/richtext.py
sphinxcontrib/bibtex/roles.py
sphinxcontrib/bibtex/transforms.py
sphinxcontrib/bibtex/style/__init__.py
sphinxcontrib/bibtex/style/template.py
sphinxcontrib/bibtex/style/names/__init__.py
sphinxcontrib/bibtex/style/names/last.py
sphinxcontrib/bibtex/style/referencing/__init__.py
sphinxcontrib/bibtex/style/referencing/author_year.py
sphinxcontrib/bibtex/style/referencing/basic_author_year.py
sphinxcontrib/bibtex/style/referencing/basic_foot.py
sphinxcontrib/bibtex/style/referencing/basic_label.py
sphinxcontrib/bibtex/style/referencing/basic_super.py
sphinxcontrib/bibtex/style/referencing/extra_author.py
sphinxcontrib/bibtex/style/referencing/extra_empty.py
sphinxcontrib/bibtex/style/referencing/extra_label.py
sphinxcontrib/bibtex/style/referencing/extra_year.py
sphinxcontrib/bibtex/style/referencing/foot.py
sphinxcontrib/bibtex/style/referencing/label.py
sphinxcontrib/bibtex/style/referencing/super_.py
sphinxcontrib_bibtex-2.6.4.dist-info/licenses/LICENSE.rst
sphinxcontrib_bibtex-2.6.4.dist-info/METADATA
sphinxcontrib_bibtex-2.6.4.dist-info/WHEEL
sphinxcontrib_bibtex-2.6.4.dist-info/entry_points.txt
sphinxcontrib_bibtex-2.6.4.dist-info/top_level.txt
sphinxcontrib_bibtex-2.6.4.dist-info/RECORD
