Metadata-Version: 2.4
Name: sphinxcontrib-bibtex
Version: 2.6.4
Summary: Sphinx extension for BibTeX style citations.
Author: Matthias C. M. Troffaes
Author-email: matthias.troffaes@gmail.com
License-Expression: BSD-2-Clause
Project-URL: homepage, https://github.com/mcmtroffaes/sphinxcontrib-bibtex
Classifier: Development Status :: 5 - Production/Stable
Classifier: Environment :: Console
Classifier: Environment :: Web Environment
Classifier: Intended Audience :: Developers
Classifier: Operating System :: OS Independent
Classifier: Programming Language :: Python
Classifier: Programming Language :: Python :: 3
Classifier: Programming Language :: Python :: 3.9
Classifier: Programming Language :: Python :: 3.10
Classifier: Programming Language :: Python :: 3.11
Classifier: Programming Language :: Python :: 3.12
Classifier: Programming Language :: Python :: 3.13
Classifier: Programming Language :: Python :: Implementation :: CPython
Classifier: Programming Language :: Python :: Implementation :: PyPy
Classifier: Topic :: Documentation
Classifier: Topic :: Utilities
Requires-Python: >=3.9
License-File: LICENSE.rst
Requires-Dist: Sphinx>=3.5
Requires-Dist: docutils!=0.18.*,!=0.19.*,>=0.8
Requires-Dist: pybtex>=0.24
Requires-Dist: pybtex-docutils>=1.0.0
Requires-Dist: importlib_metadata>=3.6; python_version < "3.10"
Requires-Dist: setuptools
Provides-Extra: test
Requires-Dist: pytest; extra == "test"
Requires-Dist: pytest-cov; extra == "test"
Requires-Dist: sphinx-autoapi; extra == "test"
Dynamic: license-file
